{"info": {"description": "", "contributor": "", "date_created": ""}, "image": {"file_name": "", "width": 500, "height": 375, "depth": 3}, "classification": [], "detection": [{"bbox": [[409, 183], [456, 217]], "category": "boat"}, {"bbox": [[417, 186], [425, 195]], "category": "boat"}, {"bbox": [[425, 186], [431, 194]], "category": "boat"}, {"bbox": [[429, 184], [434, 192]], "category": "boat"}, {"bbox": [[400, 185], [406, 193]], "category": "boat"}, {"bbox": [[368, 175], [398, 188]], "category": "boat"}, {"bbox": [[219, 175], [278, 226]], "category": "boat"}, {"bbox": [[110, 180], [140, 203]], "category": "boat"}, {"bbox": [[28, 182], [50, 201]], "category": "boat"}, {"bbox": [[291, 186], [323, 208]], "category": "boat"}, {"bbox": [[230, 184], [248, 200]], "category": "boat"}, {"bbox": [[216, 183], [234, 196]], "category": "boat"}, {"bbox": [[259, 180], [279, 189]], "category": "boat"}, {"bbox": [[269, 175], [291, 187]], "category": "boat"}], "segmentation": 0}