{"info": {"description": "", "contributor": "", "date_created": ""}, "image": {"file_name": "", "width": 500, "height": 333, "depth": 3}, "classification": [], "detection": [{"bbox": [[394, 42], [445, 234]], "category": "boat"}, {"bbox": [[353, 81], [390, 207]], "category": "boat"}, {"bbox": [[309, 52], [372, 246]], "category": "boat"}, {"bbox": [[294, 110], [324, 196]], "category": "boat"}, {"bbox": [[242, 70], [275, 212]], "category": "boat"}, {"bbox": [[230, 117], [245, 189]], "category": "boat"}, {"bbox": [[214, 112], [239, 201]], "category": "boat"}, {"bbox": [[187, 114], [210, 195]], "category": "boat"}, {"bbox": [[171, 107], [206, 223]], "category": "boat"}, {"bbox": [[137, 105], [171, 213]], "category": "boat"}, {"bbox": [[43, 224], [71, 234]], "category": "boat"}, {"bbox": [[4, 231], [29, 244]], "category": "boat"}], "segmentation": 0}